vl53l5cx_ctypes.cpython-39-arm-linux-gnueabihf.so
vl53l5cx_ctypes/__init__.py
vl53l5cx_ctypes-0.0.3.dist-info/LICENSE.txt
vl53l5cx_ctypes-0.0.3.dist-info/METADATA
vl53l5cx_ctypes-0.0.3.dist-info/WHEEL
vl53l5cx_ctypes-0.0.3.dist-info/top_level.txt
vl53l5cx_ctypes-0.0.3.dist-info/RECORD
