Metadata-Version: 2.1
Name: vl53l5cx-ctypes
Version: 0.0.3
Summary: CTypes wrapper for the Sitronix VL53L5CX 8x8 time of flight distance array "ULD" library
Home-page: https://www.pimoroni.com
Author: Philip Howard
Author-email: phil@pimoroni.com
License: MIT
Project-URL: GitHub, https://www.github.com/pimoroni/vl53l5cx-python
Keywords: Raspberry Pi
Platform: UNKNOWN
Classifier: Development Status :: 4 - Beta
Classifier: Operating System :: POSIX :: Linux
Classifier: License :: OSI Approved :: MIT License
Classifier: Intended Audience :: Developers
Classifier: Programming Language :: Python :: 3
Classifier: Topic :: Software Development
Classifier: Topic :: Software Development :: Libraries
Classifier: Topic :: System :: Hardware
Requires-Python: >=3.6
Requires-Dist: smbus2
